sensitive_info_detector/__init__.py
sensitive_info_detector/detector.py
sensitive_info_detector/patterns.py
sensitive_info_detector-1.0.dist-info/METADATA
sensitive_info_detector-1.0.dist-info/WHEEL
sensitive_info_detector-1.0.dist-info/top_level.txt
sensitive_info_detector-1.0.dist-info/RECORD
