Metadata-Version: 2.1
Name: sensitive-info-detector
Version: 1.0
Summary: A useful module for detect sensitive information/secrets 
Home-page: UNKNOWN
Author: sanket bahir
Author-email: bahirsanket2017@gmail.com
License: UNKNOWN
Platform: UNKNOWN
Requires-Python: >=3.6
Requires-Dist: black
Requires-Dist: pylint
Requires-Dist: pytest
